{
    "toplevel": "0",
    "parameters": {},
    "nodes": [
        {
            "data": {
                "id": "0",
                "name": "A0",
                "type": "or",
                "children": [
                    "72",
                    "30",
                    "22",
                    "74",
                    "96",
                    "118"
                ]
            },
            "position": {
                "x": 0,
                "y": 0
            },
            "group": "nodes"
        },
        {
            "data": {
                "id": "1",
                "name": "A1",
                "type": "be",
                "rate": "(/ 944473296573929 9444732965739290427392)",
                "dorm": "1",
                "transient": false
            },
            "position": {
                "x": 0,
                "y": 0
            },
            "group": "nodes"
        },
        {
            "data": {
                "id": "4",
                "name": "A4_A60",
                "type": "be",
                "rate": "0",
                "dorm": "1",
                "transient": false
            },
            "position": {
                "x": 0,
                "y": 0
            },
            "group": "nodes"
        },
        {
            "data": {
                "id": "5",
                "name": "A5",
                "type": "or",
                "children": [
                    "4",
                    "107",
                    "44",
                    "118"
                ]
            },
            "position": {
                "x": 0,
                "y": 0
            },
            "group": "nodes"
        },
        {
            "data": {
                "id": "6",
                "name": "A6",
                "type": "fdep",
                "children": [
                    "5",
                    "43"
                ]
            },
            "position": {
                "x": 0,
                "y": 0
            },
            "group": "nodes"
        },
        {
            "data": {
                "id": "7",
                "name": "A7_A51",
                "type": "be",
                "rate": "0",
                "dorm": "1",
                "transient": false
            },
            "position": {
                "x": 0,
                "y": 0
            },
            "group": "nodes"
        },
        {
            "data": {
                "id": "8",
                "name": "A8",
                "type": "or",
                "children": [
                    "7",
                    "107",
                    "43",
                    "118"
                ]
            },
            "position": {
                "x": 0,
                "y": 0
            },
            "group": "nodes"
        },
        {
            "data": {
                "id": "9",
                "name": "A9",
                "type": "fdep",
                "children": [
                    "8",
                    "44",
                    "49"
                ]
            },
            "position": {
                "x": 0,
                "y": 0
            },
            "group": "nodes"
        },
        {
            "data": {
                "id": "10",
                "name": "A10_A61",
                "type": "be",
                "rate": "0",
                "dorm": "1",
                "transient": false
            },
            "position": {
                "x": 0,
                "y": 0
            },
            "group": "nodes"
        },
        {
            "data": {
                "id": "11",
                "name": "A11",
                "type": "or",
                "children": [
                    "10",
                    "85",
                    "46",
                    "118"
                ]
            },
            "position": {
                "x": 0,
                "y": 0
            },
            "group": "nodes"
        },
        {
            "data": {
                "id": "12",
                "name": "A12",
                "type": "fdep",
                "children": [
                    "11",
                    "45"
                ]
            },
            "position": {
                "x": 0,
                "y": 0
            },
            "group": "nodes"
        },
        {
            "data": {
                "id": "13",
                "name": "A13_A54",
                "type": "be",
                "rate": "0",
                "dorm": "1",
                "transient": false
            },
            "position": {
                "x": 0,
                "y": 0
            },
            "group": "nodes"
        },
        {
            "data": {
                "id": "14",
                "name": "A14",
                "type": "or",
                "children": [
                    "13",
                    "85",
                    "45",
                    "118"
                ]
            },
            "position": {
                "x": 0,
                "y": 0
            },
            "group": "nodes"
        },
        {
            "data": {
                "id": "15",
                "name": "A15",
                "type": "fdep",
                "children": [
                    "14",
                    "46",
                    "52"
                ]
            },
            "position": {
                "x": 0,
                "y": 0
            },
            "group": "nodes"
        },
        {
            "data": {
                "id": "16",
                "name": "A16_A62",
                "type": "be",
                "rate": "0",
                "dorm": "1",
                "transient": false
            },
            "position": {
                "x": 0,
                "y": 0
            },
            "group": "nodes"
        },
        {
            "data": {
                "id": "17",
                "name": "A17",
                "type": "or",
                "children": [
                    "16",
                    "96",
                    "48",
                    "118"
                ]
            },
            "position": {
                "x": 0,
                "y": 0
            },
            "group": "nodes"
        },
        {
            "data": {
                "id": "18",
                "name": "A18",
                "type": "fdep",
                "children": [
                    "17",
                    "47"
                ]
            },
            "position": {
                "x": 0,
                "y": 0
            },
            "group": "nodes"
        },
        {
            "data": {
                "id": "19",
                "name": "A19_A57",
                "type": "be",
                "rate": "0",
                "dorm": "1",
                "transient": false
            },
            "position": {
                "x": 0,
                "y": 0
            },
            "group": "nodes"
        },
        {
            "data": {
                "id": "20",
                "name": "A20",
                "type": "or",
                "children": [
                    "19",
                    "96",
                    "47"
                ]
            },
            "position": {
                "x": 0,
                "y": 0
            },
            "group": "nodes"
        },
        {
            "data": {
                "id": "21",
                "name": "A21",
                "type": "fdep",
                "children": [
                    "20",
                    "48",
                    "55"
                ]
            },
            "position": {
                "x": 0,
                "y": 0
            },
            "group": "nodes"
        },
        {
            "data": {
                "id": "22",
                "name": "A22_A59_A25_A58_A63_A28_A64_A33_A65_A36_A66_A39",
                "type": "be",
                "rate": "(/ 944473296573929 1180591620717411303424)",
                "dorm": "1",
                "transient": false
            },
            "position": {
                "x": 0,
                "y": 0
            },
            "group": "nodes"
        },
        {
            "data": {
                "id": "29",
                "name": "A29",
                "type": "be",
                "rate": "(/ 944473296573929 9444732965739290427392)",
                "dorm": "1",
                "transient": false
            },
            "position": {
                "x": 0,
                "y": 0
            },
            "group": "nodes"
        },
        {
            "data": {
                "id": "30",
                "name": "A30",
                "type": "vot",
                "children": [
                    "29",
                    "68",
                    "1",
                    "67"
                ],
                "voting": "3"
            },
            "position": {
                "x": 0,
                "y": 0
            },
            "group": "nodes"
        },
        {
            "data": {
                "id": "40",
                "name": "A40",
                "type": "or",
                "children": [
                    "17",
                    "20"
                ]
            },
            "position": {
                "x": 0,
                "y": 0
            },
            "group": "nodes"
        },
        {
            "data": {
                "id": "43",
                "name": "A43",
                "type": "be",
                "rate": "0",
                "dorm": "1",
                "transient": false
            },
            "position": {
                "x": 0,
                "y": 0
            },
            "group": "nodes"
        },
        {
            "data": {
                "id": "44",
                "name": "A44",
                "type": "be",
                "rate": "0",
                "dorm": "1",
                "transient": false
            },
            "position": {
                "x": 0,
                "y": 0
            },
            "group": "nodes"
        },
        {
            "data": {
                "id": "45",
                "name": "A45",
                "type": "be",
                "rate": "0",
                "dorm": "1",
                "transient": false
            },
            "position": {
                "x": 0,
                "y": 0
            },
            "group": "nodes"
        },
        {
            "data": {
                "id": "46",
                "name": "A46",
                "type": "be",
                "rate": "0",
                "dorm": "1",
                "transient": false
            },
            "position": {
                "x": 0,
                "y": 0
            },
            "group": "nodes"
        },
        {
            "data": {
                "id": "47",
                "name": "A47",
                "type": "be",
                "rate": "0",
                "dorm": "1",
                "transient": false
            },
            "position": {
                "x": 0,
                "y": 0
            },
            "group": "nodes"
        },
        {
            "data": {
                "id": "48",
                "name": "A48",
                "type": "be",
                "rate": "0",
                "dorm": "1",
                "transient": false
            },
            "position": {
                "x": 0,
                "y": 0
            },
            "group": "nodes"
        },
        {
            "data": {
                "id": "49",
                "name": "A49",
                "type": "be",
                "rate": "0",
                "dorm": "1",
                "transient": false
            },
            "position": {
                "x": 0,
                "y": 0
            },
            "group": "nodes"
        },
        {
            "data": {
                "id": "50",
                "name": "A50",
                "type": "or",
                "children": [
                    "49",
                    "118"
                ]
            },
            "position": {
                "x": 0,
                "y": 0
            },
            "group": "nodes"
        },
        {
            "data": {
                "id": "52",
                "name": "A52",
                "type": "be",
                "rate": "0",
                "dorm": "1",
                "transient": false
            },
            "position": {
                "x": 0,
                "y": 0
            },
            "group": "nodes"
        },
        {
            "data": {
                "id": "53",
                "name": "A53",
                "type": "or",
                "children": [
                    "52",
                    "118"
                ]
            },
            "position": {
                "x": 0,
                "y": 0
            },
            "group": "nodes"
        },
        {
            "data": {
                "id": "55",
                "name": "A55",
                "type": "be",
                "rate": "0",
                "dorm": "1",
                "transient": false
            },
            "position": {
                "x": 0,
                "y": 0
            },
            "group": "nodes"
        },
        {
            "data": {
                "id": "56",
                "name": "A56",
                "type": "or",
                "children": [
                    "55",
                    "96"
                ]
            },
            "position": {
                "x": 0,
                "y": 0
            },
            "group": "nodes"
        },
        {
            "data": {
                "id": "67",
                "name": "A67",
                "type": "be",
                "rate": "(/ 944473296573929 9444732965739290427392)",
                "dorm": "1",
                "transient": false
            },
            "position": {
                "x": 0,
                "y": 0
            },
            "group": "nodes"
        },
        {
            "data": {
                "id": "68",
                "name": "A68",
                "type": "be",
                "rate": "(/ 944473296573929 9444732965739290427392)",
                "dorm": "1",
                "transient": false
            },
            "position": {
                "x": 0,
                "y": 0
            },
            "group": "nodes"
        },
        {
            "data": {
                "id": "69",
                "name": "A69",
                "type": "or",
                "children": [
                    "5",
                    "8"
                ]
            },
            "position": {
                "x": 0,
                "y": 0
            },
            "group": "nodes"
        },
        {
            "data": {
                "id": "70",
                "name": "A70",
                "type": "or",
                "children": [
                    "11",
                    "14"
                ]
            },
            "position": {
                "x": 0,
                "y": 0
            },
            "group": "nodes"
        },
        {
            "data": {
                "id": "71",
                "name": "A71",
                "type": "and",
                "children": [
                    "70",
                    "40"
                ]
            },
            "position": {
                "x": 0,
                "y": 0
            },
            "group": "nodes"
        },
        {
            "data": {
                "id": "72",
                "name": "A72",
                "type": "and",
                "children": [
                    "69",
                    "71"
                ]
            },
            "position": {
                "x": 0,
                "y": 0
            },
            "group": "nodes"
        },
        {
            "data": {
                "id": "73",
                "name": "A73",
                "type": "and",
                "children": [
                    "53",
                    "56"
                ]
            },
            "position": {
                "x": 0,
                "y": 0
            },
            "group": "nodes"
        },
        {
            "data": {
                "id": "74",
                "name": "A74",
                "type": "and",
                "children": [
                    "50",
                    "73"
                ]
            },
            "position": {
                "x": 0,
                "y": 0
            },
            "group": "nodes"
        },
        {
            "data": {
                "id": "75",
                "name": "A75",
                "type": "be",
                "rate": "(/ 2921964261275593 295147905179352825856)",
                "dorm": "1",
                "transient": true
            },
            "position": {
                "x": 0,
                "y": 0
            },
            "group": "nodes"
        },
        {
            "data": {
                "id": "76",
                "name": "A76",
                "type": "be",
                "rate": "(/ 7555786372591439 75557863725914323419136)",
                "dorm": "1",
                "transient": true
            },
            "position": {
                "x": 0,
                "y": 0
            },
            "group": "nodes"
        },
        {
            "data": {
                "id": "77",
                "name": "A77",
                "type": "be",
                "rate": "(/ 4722366482869645 4722366482869645213696)",
                "dorm": "1",
                "transient": false
            },
            "position": {
                "x": 0,
                "y": 0
            },
            "group": "nodes"
        },
        {
            "data": {
                "id": "78",
                "name": "A78",
                "type": "and",
                "children": [
                    "77",
                    "75"
                ]
            },
            "position": {
                "x": 0,
                "y": 0
            },
            "group": "nodes"
        },
        {
            "data": {
                "id": "79",
                "name": "A79",
                "type": "seq",
                "children": [
                    "77",
                    "75"
                ]
            },
            "position": {
                "x": 0,
                "y": 0
            },
            "group": "nodes"
        },
        {
            "data": {
                "id": "80",
                "name": "A80",
                "type": "be",
                "rate": "(/ 4675142818040949 4722366482869645213696)",
                "dorm": "1",
                "transient": false
            },
            "position": {
                "x": 0,
                "y": 0
            },
            "group": "nodes"
        },
        {
            "data": {
                "id": "81",
                "name": "A81",
                "type": "be",
                "rate": "(/ 6044629098073151 604462909807314587353088)",
                "dorm": "1",
                "transient": false
            },
            "position": {
                "x": 0,
                "y": 0
            },
            "group": "nodes"
        },
        {
            "data": {
                "id": "82",
                "name": "A82",
                "type": "be",
                "rate": "(/ 4722366482869645 4722366482869645213696)",
                "dorm": "1",
                "transient": false
            },
            "position": {
                "x": 0,
                "y": 0
            },
            "group": "nodes"
        },
        {
            "data": {
                "id": "83",
                "name": "A83",
                "type": "and",
                "children": [
                    "82",
                    "80"
                ]
            },
            "position": {
                "x": 0,
                "y": 0
            },
            "group": "nodes"
        },
        {
            "data": {
                "id": "84",
                "name": "A84",
                "type": "seq",
                "children": [
                    "82",
                    "80"
                ]
            },
            "position": {
                "x": 0,
                "y": 0
            },
            "group": "nodes"
        },
        {
            "data": {
                "id": "85",
                "name": "A85",
                "type": "or",
                "children": [
                    "76",
                    "78",
                    "81",
                    "83"
                ]
            },
            "position": {
                "x": 0,
                "y": 0
            },
            "group": "nodes"
        },
        {
            "data": {
                "id": "86",
                "name": "A86",
                "type": "be",
                "rate": "(/ 2921964261275593 295147905179352825856)",
                "dorm": "1",
                "transient": true
            },
            "position": {
                "x": 0,
                "y": 0
            },
            "group": "nodes"
        },
        {
            "data": {
                "id": "87",
                "name": "A87",
                "type": "be",
                "rate": "(/ 7555786372591439 75557863725914323419136)",
                "dorm": "1",
                "transient": true
            },
            "position": {
                "x": 0,
                "y": 0
            },
            "group": "nodes"
        },
        {
            "data": {
                "id": "88",
                "name": "A88",
                "type": "be",
                "rate": "(/ 4722366482869645 4722366482869645213696)",
                "dorm": "1",
                "transient": false
            },
            "position": {
                "x": 0,
                "y": 0
            },
            "group": "nodes"
        },
        {
            "data": {
                "id": "89",
                "name": "A89",
                "type": "and",
                "children": [
                    "88",
                    "86"
                ]
            },
            "position": {
                "x": 0,
                "y": 0
            },
            "group": "nodes"
        },
        {
            "data": {
                "id": "90",
                "name": "A90",
                "type": "seq",
                "children": [
                    "88",
                    "86"
                ]
            },
            "position": {
                "x": 0,
                "y": 0
            },
            "group": "nodes"
        },
        {
            "data": {
                "id": "91",
                "name": "A91",
                "type": "be",
                "rate": "(/ 4675142818040949 4722366482869645213696)",
                "dorm": "1",
                "transient": false
            },
            "position": {
                "x": 0,
                "y": 0
            },
            "group": "nodes"
        },
        {
            "data": {
                "id": "92",
                "name": "A92",
                "type": "be",
                "rate": "(/ 6044629098073151 604462909807314587353088)",
                "dorm": "1",
                "transient": false
            },
            "position": {
                "x": 0,
                "y": 0
            },
            "group": "nodes"
        },
        {
            "data": {
                "id": "93",
                "name": "A93",
                "type": "be",
                "rate": "(/ 4722366482869645 4722366482869645213696)",
                "dorm": "1",
                "transient": false
            },
            "position": {
                "x": 0,
                "y": 0
            },
            "group": "nodes"
        },
        {
            "data": {
                "id": "94",
                "name": "A94",
                "type": "and",
                "children": [
                    "93",
                    "91"
                ]
            },
            "position": {
                "x": 0,
                "y": 0
            },
            "group": "nodes"
        },
        {
            "data": {
                "id": "95",
                "name": "A95",
                "type": "seq",
                "children": [
                    "93",
                    "91"
                ]
            },
            "position": {
                "x": 0,
                "y": 0
            },
            "group": "nodes"
        },
        {
            "data": {
                "id": "96",
                "name": "A96",
                "type": "or",
                "children": [
                    "87",
                    "89",
                    "92",
                    "94"
                ]
            },
            "position": {
                "x": 0,
                "y": 0
            },
            "group": "nodes"
        },
        {
            "data": {
                "id": "97",
                "name": "A97",
                "type": "be",
                "rate": "(/ 1106804644422573 18446744073709551616)",
                "dorm": "1",
                "transient": true
            },
            "position": {
                "x": 0,
                "y": 0
            },
            "group": "nodes"
        },
        {
            "data": {
                "id": "98",
                "name": "A98",
                "type": "be",
                "rate": "(/ 5902958103587057 147573952589676412928)",
                "dorm": "1",
                "transient": true
            },
            "position": {
                "x": 0,
                "y": 0
            },
            "group": "nodes"
        },
        {
            "data": {
                "id": "99",
                "name": "A99",
                "type": "be",
                "rate": "(/ 5902958103587057 590295810358705651712)",
                "dorm": "1",
                "transient": false
            },
            "position": {
                "x": 0,
                "y": 0
            },
            "group": "nodes"
        },
        {
            "data": {
                "id": "100",
                "name": "A100",
                "type": "and",
                "children": [
                    "99",
                    "97"
                ]
            },
            "position": {
                "x": 0,
                "y": 0
            },
            "group": "nodes"
        },
        {
            "data": {
                "id": "101",
                "name": "A101",
                "type": "seq",
                "children": [
                    "99",
                    "97"
                ]
            },
            "position": {
                "x": 0,
                "y": 0
            },
            "group": "nodes"
        },
        {
            "data": {
                "id": "102",
                "name": "A102",
                "type": "be",
                "rate": "(/ 1770887431076117 295147905179352825856)",
                "dorm": "1",
                "transient": false
            },
            "position": {
                "x": 0,
                "y": 0
            },
            "group": "nodes"
        },
        {
            "data": {
                "id": "103",
                "name": "A103",
                "type": "be",
                "rate": "(/ 4722366482869645 1180591620717411303424)",
                "dorm": "1",
                "transient": false
            },
            "position": {
                "x": 0,
                "y": 0
            },
            "group": "nodes"
        },
        {
            "data": {
                "id": "104",
                "name": "A104",
                "type": "be",
                "rate": "(/ 5902958103587057 590295810358705651712)",
                "dorm": "1",
                "transient": false
            },
            "position": {
                "x": 0,
                "y": 0
            },
            "group": "nodes"
        },
        {
            "data": {
                "id": "105",
                "name": "A105",
                "type": "and",
                "children": [
                    "104",
                    "102"
                ]
            },
            "position": {
                "x": 0,
                "y": 0
            },
            "group": "nodes"
        },
        {
            "data": {
                "id": "106",
                "name": "A106",
                "type": "seq",
                "children": [
                    "104",
                    "102"
                ]
            },
            "position": {
                "x": 0,
                "y": 0
            },
            "group": "nodes"
        },
        {
            "data": {
                "id": "107",
                "name": "A107",
                "type": "or",
                "children": [
                    "98",
                    "100",
                    "103",
                    "105"
                ]
            },
            "position": {
                "x": 0,
                "y": 0
            },
            "group": "nodes"
        },
        {
            "data": {
                "id": "108",
                "name": "A108",
                "type": "be",
                "rate": "(/ 2921964261275593 295147905179352825856)",
                "dorm": "1",
                "transient": true
            },
            "position": {
                "x": 0,
                "y": 0
            },
            "group": "nodes"
        },
        {
            "data": {
                "id": "109",
                "name": "A109",
                "type": "be",
                "rate": "(/ 7555786372591439 75557863725914323419136)",
                "dorm": "1",
                "transient": true
            },
            "position": {
                "x": 0,
                "y": 0
            },
            "group": "nodes"
        },
        {
            "data": {
                "id": "110",
                "name": "A110",
                "type": "be",
                "rate": "(/ 4722366482869645 4722366482869645213696)",
                "dorm": "1",
                "transient": false
            },
            "position": {
                "x": 0,
                "y": 0
            },
            "group": "nodes"
        },
        {
            "data": {
                "id": "111",
                "name": "A111",
                "type": "and",
                "children": [
                    "110",
                    "108"
                ]
            },
            "position": {
                "x": 0,
                "y": 0
            },
            "group": "nodes"
        },
        {
            "data": {
                "id": "112",
                "name": "A112",
                "type": "seq",
                "children": [
                    "110",
                    "108"
                ]
            },
            "position": {
                "x": 0,
                "y": 0
            },
            "group": "nodes"
        },
        {
            "data": {
                "id": "113",
                "name": "A113",
                "type": "be",
                "rate": "(/ 4675142818040949 4722366482869645213696)",
                "dorm": "1",
                "transient": false
            },
            "position": {
                "x": 0,
                "y": 0
            },
            "group": "nodes"
        },
        {
            "data": {
                "id": "114",
                "name": "A114",
                "type": "be",
                "rate": "(/ 6044629098073151 604462909807314587353088)",
                "dorm": "1",
                "transient": false
            },
            "position": {
                "x": 0,
                "y": 0
            },
            "group": "nodes"
        },
        {
            "data": {
                "id": "115",
                "name": "A115",
                "type": "be",
                "rate": "(/ 4722366482869645 4722366482869645213696)",
                "dorm": "1",
                "transient": false
            },
            "position": {
                "x": 0,
                "y": 0
            },
            "group": "nodes"
        },
        {
            "data": {
                "id": "116",
                "name": "A116",
                "type": "and",
                "children": [
                    "115",
                    "113"
                ]
            },
            "position": {
                "x": 0,
                "y": 0
            },
            "group": "nodes"
        },
        {
            "data": {
                "id": "117",
                "name": "A117",
                "type": "seq",
                "children": [
                    "115",
                    "113"
                ]
            },
            "position": {
                "x": 0,
                "y": 0
            },
            "group": "nodes"
        },
        {
            "data": {
                "id": "118",
                "name": "A118",
                "type": "or",
                "children": [
                    "109",
                    "111",
                    "114",
                    "116"
                ]
            },
            "position": {
                "x": 0,
                "y": 0
            },
            "group": "nodes"
        }
    ]
}